capability_statement_generator.py
capability_statement_generator-1.0.0.dist-info/licenses/LICENSE
capability_statement_generator-1.0.0.dist-info/METADATA
capability_statement_generator-1.0.0.dist-info/WHEEL
capability_statement_generator-1.0.0.dist-info/entry_points.txt
capability_statement_generator-1.0.0.dist-info/top_level.txt
capability_statement_generator-1.0.0.dist-info/RECORD
