Metadata-Version: 2.4
Name: capability-statement-generator
Version: 1.0.0
Summary: Automated form creation and data population for company capability statements
Home-page: https://github.com/yourusername/capability-statement-generator
Author: Capability Statement Generator Team
Author-email: developer@pharmatech.com
Project-URL: Bug Reports, https://github.com/yourusername/capability-statement-generator/issues
Project-URL: Source, https://github.com/yourusername/capability-statement-generator
Project-URL: Documentation, https://github.com/yourusername/capability-statement-generator#readme
Keywords: capability statement,business documents,form generator,automation,json export
Classifier: Development Status :: 5 - Production/Stable
Classifier: Intended Audience :: Developers
Classifier: Intended Audience :: End Users/Desktop
Classifier: License :: OSI Approved :: MIT License
Classifier: Operating System :: OS Independent
Classifier: Programming Language :: Python :: 3
Classifier: Programming Language :: Python :: 3.7
Classifier: Programming Language :: Python :: 3.8
Classifier: Programming Language :: Python :: 3.9
Classifier: Programming Language :: Python :: 3.10
Classifier: Programming Language :: Python :: 3.11
Classifier: Programming Language :: Python :: 3.12
Classifier: Topic :: Office/Business
Classifier: Topic :: Software Development :: Libraries :: Python Modules
Classifier: Topic :: Text Processing
Classifier: Topic :: Utilities
Requires-Python: >=3.7
License-File: LICENSE
Dynamic: author
Dynamic: author-email
Dynamic: classifier
Dynamic: description
Dynamic: description-content-type
Dynamic: home-page
Dynamic: keywords
Dynamic: license-file
Dynamic: project-url
Dynamic: requires-python
Dynamic: summary
